pymc_ext/__init__.py
pymc_ext/distributions.py
pymc_ext/optim.py
pymc_ext/pymc_ext_version.py
pymc_ext/utils.py
pymc_ext-1.0.1.dist-info/LICENSE
pymc_ext-1.0.1.dist-info/METADATA
pymc_ext-1.0.1.dist-info/WHEEL
pymc_ext-1.0.1.dist-info/top_level.txt
pymc_ext-1.0.1.dist-info/RECORD
