Metadata-Version: 2.1
Name: pymc_ext
Version: 1.0.1
Summary: PyMC Extras extracted from the 
Home-page: https://github.com/exoplanet-dev/pymc-ext
Author: Daniel Foreman-Mackey
Author-email: foreman.mackey@gmail.com
Maintainer: Daniel Foreman-Mackey
Maintainer-email: foreman.mackey@gmail.com
License: MIT
Classifier: Development Status :: 4 - Beta
Classifier: Intended Audience :: Developers
Classifier: Intended Audience :: Science/Research
Classifier: License :: OSI Approved :: MIT License
Classifier: Operating System :: OS Independent
Classifier: Programming Language :: Python
Classifier: Programming Language :: Python :: 3
License-File: LICENSE
Requires-Dist: pymc >=5.0.0
Provides-Extra: notebooks
Requires-Dist: nbconvert ; extra == 'notebooks'
Requires-Dist: jupytext ; extra == 'notebooks'
Requires-Dist: ipykernel ; extra == 'notebooks'
Provides-Extra: test
Requires-Dist: pytest ; extra == 'test'
